README.md
setup.cfg
setup.py
distributions_ga_bi/Binomialdistribution.py
distributions_ga_bi/Gaussiandistribution.py
distributions_ga_bi/Generaldistribution.py
distributions_ga_bi/__init__.py
distributions_ga_bi.egg-info/PKG-INFO
distributions_ga_bi.egg-info/SOURCES.txt
distributions_ga_bi.egg-info/dependency_links.txt
distributions_ga_bi.egg-info/not-zip-safe
distributions_ga_bi.egg-info/top_level.txt